modoboa_contacts/__init__.py
modoboa_contacts/apps.py
modoboa_contacts/constants.py
modoboa_contacts/factories.py
modoboa_contacts/forms.py
modoboa_contacts/handlers.py
modoboa_contacts/mocks.py
modoboa_contacts/models.py
modoboa_contacts/modo_extension.py
modoboa_contacts/serializers.py
modoboa_contacts/settings.py
modoboa_contacts/tasks.py
modoboa_contacts/tests.py
modoboa_contacts/urls.py
modoboa_contacts/urls_api.py
modoboa_contacts/version.py
modoboa_contacts/views.py
modoboa_contacts/viewsets.py
modoboa_contacts/importer/__init__.py
modoboa_contacts/importer/backends/__init__.py
modoboa_contacts/importer/backends/outlook.py
modoboa_contacts/lib/__init__.py
modoboa_contacts/lib/carddav.py
modoboa_contacts/locale/br/LC_MESSAGES/django.mo
modoboa_contacts/locale/br/LC_MESSAGES/django.po
modoboa_contacts/locale/en/LC_MESSAGES/django.mo
modoboa_contacts/locale/en/LC_MESSAGES/django.po
modoboa_contacts/locale/es/LC_MESSAGES/django.mo
modoboa_contacts/locale/es/LC_MESSAGES/django.po
modoboa_contacts/locale/fr/LC_MESSAGES/django.mo
modoboa_contacts/locale/fr/LC_MESSAGES/django.po
modoboa_contacts/locale/it/LC_MESSAGES/django.mo
modoboa_contacts/locale/it/LC_MESSAGES/django.po
modoboa_contacts/locale/pl_PL/LC_MESSAGES/django.mo
modoboa_contacts/locale/pl_PL/LC_MESSAGES/django.po
modoboa_contacts/management/__init__.py
modoboa_contacts/management/commands/__init__.py
modoboa_contacts/management/commands/import_contacts.py
modoboa_contacts/migrations/0001_initial.py
modoboa_contacts/migrations/0002_auto_20180124_2311.py
modoboa_contacts/migrations/0003_auto_20181005_1415.py
modoboa_contacts/migrations/0004_auto_20181005_1415.py
modoboa_contacts/migrations/0005_auto_20181005_1445.py
modoboa_contacts/migrations/0006_alter_phonenumber_type.py
modoboa_contacts/migrations/0007_alter_contact_address.py
modoboa_contacts/migrations/__init__.py
modoboa_contacts/static/index.html
modoboa_contacts/static/modoboa_contacts/webpack-stats.json
modoboa_contacts-1.1.3.dist-info/LICENSE
modoboa_contacts-1.1.3.dist-info/METADATA
modoboa_contacts-1.1.3.dist-info/WHEEL
modoboa_contacts-1.1.3.dist-info/top_level.txt
modoboa_contacts-1.1.3.dist-info/RECORD
